tesseract_streamlit/__init__.py
tesseract_streamlit/_version.py
tesseract_streamlit/cli.py
tesseract_streamlit/config.py
tesseract_streamlit/parse.py
tesseract_streamlit/resources/favicon.ico
tesseract_streamlit/templates/template.j2
tesseract_streamlit-0.1.0.dist-info/licenses/LICENSE
tesseract_streamlit-0.1.0.dist-info/METADATA
tesseract_streamlit-0.1.0.dist-info/WHEEL
tesseract_streamlit-0.1.0.dist-info/entry_points.txt
tesseract_streamlit-0.1.0.dist-info/top_level.txt
tesseract_streamlit-0.1.0.dist-info/RECORD
