Metadata-Version: 2.4
Name: tesseract-streamlit
Version: 0.1.0
Summary: Tesseract Streamlit automatically generates Streamlit apps from Tesseract APIs.
Author-email: "The tesseract-streamlit team @ Pasteur Labs" <info@simulation.science>
Project-URL: Homepage, https://github.com/pasteurlabs/tesseract-streamlit
Requires-Python: <3.14,>=3.10
License-File: LICENSE
Requires-Dist: streamlit
Requires-Dist: tesseract-core
Requires-Dist: jinja2
Requires-Dist: numpy
Requires-Dist: pyvista[jupyter]
Requires-Dist: stpyvista
Requires-Dist: typing-extensions
Requires-Dist: requests
Requires-Dist: click
Requires-Dist: orjson
Requires-Dist: platformdirs
Provides-Extra: docs
Requires-Dist: sphinx; extra == "docs"
Requires-Dist: sphinx_autodoc_typehints; extra == "docs"
Requires-Dist: furo; extra == "docs"
Requires-Dist: myst-parser; extra == "docs"
Provides-Extra: dev
Requires-Dist: pre-commit; extra == "dev"
Requires-Dist: pytest; extra == "dev"
Requires-Dist: pytest-cov; extra == "dev"
Requires-Dist: typeguard; extra == "dev"
Requires-Dist: matplotlib; extra == "dev"
Requires-Dist: pyyaml; extra == "dev"
Requires-Dist: tesseract-streamlit[docs]; extra == "dev"
Dynamic: license-file
